{"GlobalPropertiesHash":"pMkoX0Wg87dqtQrQEk6fMxaLIkps3BeAIDs2vhvGrPQ=","FingerprintPatternsHash":"gq3WsqcKBUGTSNle7RKKyXRIwh7M8ccEqOqYvIzoM04=","PropertyOverridesHash":"8ZRc1sGeVrPBx4lD717BgRaQekyh78QKV9SKsdt638U=","InputHashes":["rkWZ1BqiPcAEWM/H6oHK1bFrAXsAnscbMc/MGjGLMiY=","gvTazp/\u002BPPVIY0jqyJmnJJ19meh2qHadpAg13pdmAAc=","xG3FLzdu24/KQxORDBnffXJL7GS2JTWtkuXfdQWvMHk=","73of5KSPAcuTFDuTYfvwS1p9sMMsTNC7gH/fP/PGSoE=","EoWZVnFej7VTJVzN7TTPzRf7DNeKbIVY8WEC9nl\u002B7aI=","fbpW9ab7L1TaTnBuwiQwMgqEzT06/9VPn3k/59XfidI=","nItXDEA1DeleaiS9Lf9hU0aQRZvq\u002Bg2YciN97ML78kU=","A8qVIH4AQ8ZeGJP8hU\u002BDgTDHZarVh0EeyS81XZa1QiY=","OS5oPSXSHvBGniXKwUR4s/TOv\u002BMl/uBJZoB9H\u002BAju3k=","pf1/LId9cMv4\u002BKfSpl9vDNp/3iCmekL4pPybwRqzkHQ=","R3QorycGvgV8LgfQhbXzgHkXPpI/LdEGN/s\u002Be3oaOB4=","hHYEBssbyj\u002BAB4XInZ/C\u002B0lAa7PTGfDAcJF75pH89tg=","86UXLN0VsXeD05sU3sZBg33LTlPOtcxT2ewkBd7xloU=","FoEgunFimqb2nmqWmtBZ3MgsB3YFgLmCNyexXEQl20Q=","KMF0x6KVdm5kW4UEzhnsnRLVdT0gIEaWkbwwVUBY/XQ=","o6Pw\u002BWEWGKy9wkWUfOE\u002BHYnAssDi62RF2Ai8tCuJ9Ic=","PbZCF/3D0Mbo7UYP\u002B2Zf6lAFzOuBwpC9sUwzRR/cpW8=","HiTxlUnTXuQbm2l/MSBCJbfFBDv4d2XyWq4ZJPgC0F4=","zajGcXyfa5\u002BtC9UY35hn\u002BDnwdnCJJJ81SS95cRItiro=","PFV4kHpoKnYvrYVcP9Hjzl9R1SN598aybalaWiwBGos=","gsFINd58jSq7BGIdENZ\u002BWBgVsYvGKAsGYGb12nejp1g=","hVr2p/kepa/tB7pLVzqmsRvwEAJ6\u002BjL7S4bkrsKtqoA=","4llHrNd/dL6A0raNiBJx7TYAMIehDU1SfnD\u002BtbgiYD8=","qE1iElOjEXSKtxzbhgyJ5xYqaPhs54TJeoeI7A/SYMs=","o694Z81kabHaRNXmVBa3JVpubpMZ5aKM7Uq0dLfC21o=","cKlTUJsDyWwF95OfZvl8kv0owqW9D6Xlp7dhf4ujwiI=","2aN7HIQRyW5LnaTnFE/heHFO/DxrhDh5FhkyUg\u002BI1cc=","lgOkF0L/gx8jTilTdfFLg9AtnBKQObxY3LwrNOG0e6k=","3xWAqPu9FwSDRF1o708eyLCdkwX59JsGIcSL3SAHGjA=","YdJz7A8xQXa\u002BFqgBGEd9pDGRsoLq1ympYzAL2vlRkgg="],"CachedAssets":{"rkWZ1BqiPcAEWM/H6oHK1bFrAXsAnscbMc/MGjGLMiY=":{"Identity":"C:\\Users\\53450061801\\Desktop\\TantoFaz\\Projeto-Grupo-Senai\\Back-End\\wwwroot\\assets\\1158 - 1 - Edited.png","SourceId":"BackEndProjeto","SourceType":"Discovered","ContentRoot":"C:\\Users\\53450061801\\Desktop\\TantoFaz\\Projeto-Grupo-Senai\\Back-End\\wwwroot\\","BasePath":"_content/BackEndProjeto","RelativePath":"assets/1158 - 1 - Edited#[.{fingerprint}]?.png","AssetKind":"All","AssetMode":"All","AssetRole":"Primary","AssetMergeBehavior":null,"AssetMergeSource":"","RelatedAsset":null,"AssetTraitName":null,"AssetTraitValue":null,"Fingerprint":"ke22kbvx2d","Integrity":"rEhmiU2azGQremp66LDCPwA4q/ccYCXUQll9CTx\u002B7Vw=","CopyToOutputDirectory":"Never","CopyToPublishDirectory":"PreserveNewest","OriginalItemSpec":"wwwroot\\assets\\1158 - 1 - Edited.png","FileLength":144319,"LastWriteTime":"2025-12-08T13:40:10.487016+00:00"},"gvTazp/\u002BPPVIY0jqyJmnJJ19meh2qHadpAg13pdmAAc=":{"Identity":"C:\\Users\\53450061801\\Desktop\\TantoFaz\\Projeto-Grupo-Senai\\Back-End\\wwwroot\\assets\\1158.png","SourceId":"BackEndProjeto","SourceType":"Discovered","ContentRoot":"C:\\Users\\53450061801\\Desktop\\TantoFaz\\Projeto-Grupo-Senai\\Back-End\\wwwroot\\","BasePath":"_content/BackEndProjeto","RelativePath":"assets/1158#[.{fingerprint}]?.png","AssetKind":"All","AssetMode":"All","AssetRole":"Primary","AssetMergeBehavior":null,"AssetMergeSource":"","RelatedAsset":null,"AssetTraitName":null,"AssetTraitValue":null,"Fingerprint":"c960srp4gw","Integrity":"sJc\u002BhLPBmAE3vqEzA7G/vNHRpiRv85ajflwpMoruSMM=","CopyToOutputDirectory":"Never","CopyToPublishDirectory":"PreserveNewest","OriginalItemSpec":"wwwroot\\assets\\1158.png","FileLength":139437,"LastWriteTime":"2025-12-08T13:40:10.487016+00:00"},"xG3FLzdu24/KQxORDBnffXJL7GS2JTWtkuXfdQWvMHk=":{"Identity":"C:\\Users\\53450061801\\Desktop\\TantoFaz\\Projeto-Grupo-Senai\\Back-End\\wwwroot\\assets\\bg.png","SourceId":"BackEndProjeto","SourceType":"Discovered","ContentRoot":"C:\\Users\\53450061801\\Desktop\\TantoFaz\\Projeto-Grupo-Senai\\Back-End\\wwwroot\\","BasePath":"_content/BackEndProjeto","RelativePath":"assets/bg#[.{fingerprint}]?.png","AssetKind":"All","AssetMode":"All","AssetRole":"Primary","AssetMergeBehavior":null,"AssetMergeSource":"","RelatedAsset":null,"AssetTraitName":null,"AssetTraitValue":null,"Fingerprint":"f2bes3xqn8","Integrity":"ebj9qFgcMXnV1e6KMdeBH/5oyCU6FdW\u002BxdQ/SAcJv2g=","CopyToOutputDirectory":"Never","CopyToPublishDirectory":"PreserveNewest","OriginalItemSpec":"wwwroot\\assets\\bg.png","FileLength":6341948,"LastWriteTime":"2025-12-08T13:40:10.5343108+00:00"},"73of5KSPAcuTFDuTYfvwS1p9sMMsTNC7gH/fP/PGSoE=":{"Identity":"C:\\Users\\53450061801\\Desktop\\TantoFaz\\Projeto-Grupo-Senai\\Back-End\\wwwroot\\assets\\buttomA.png","SourceId":"BackEndProjeto","SourceType":"Discovered","ContentRoot":"C:\\Users\\53450061801\\Desktop\\TantoFaz\\Projeto-Grupo-Senai\\Back-End\\wwwroot\\","BasePath":"_content/BackEndProjeto","RelativePath":"assets/buttomA#[.{fingerprint}]?.png","AssetKind":"All","AssetMode":"All","AssetRole":"Primary","AssetMergeBehavior":null,"AssetMergeSource":"","RelatedAsset":null,"AssetTraitName":null,"AssetTraitValue":null,"Fingerprint":"uszotjut5n","Integrity":"wqua2KFwInu3RcjpEBw//qxs\u002BQ67P4pHGHDTwa8YWso=","CopyToOutputDirectory":"Never","CopyToPublishDirectory":"PreserveNewest","OriginalItemSpec":"wwwroot\\assets\\buttomA.png","FileLength":32639,"LastWriteTime":"2025-12-08T13:40:10.5343108+00:00"},"EoWZVnFej7VTJVzN7TTPzRf7DNeKbIVY8WEC9nl\u002B7aI=":{"Identity":"C:\\Users\\53450061801\\Desktop\\TantoFaz\\Projeto-Grupo-Senai\\Back-End\\wwwroot\\assets\\buttomB.png","SourceId":"BackEndProjeto","SourceType":"Discovered","ContentRoot":"C:\\Users\\53450061801\\Desktop\\TantoFaz\\Projeto-Grupo-Senai\\Back-End\\wwwroot\\","BasePath":"_content/BackEndProjeto","RelativePath":"assets/buttomB#[.{fingerprint}]?.png","AssetKind":"All","AssetMode":"All","AssetRole":"Primary","AssetMergeBehavior":null,"AssetMergeSource":"","RelatedAsset":null,"AssetTraitName":null,"AssetTraitValue":null,"Fingerprint":"th1r4ugugm","Integrity":"UXz9SM9d048k57/xLjWHeVQK31y03F/gwAIXXZoC/NI=","CopyToOutputDirectory":"Never","CopyToPublishDirectory":"PreserveNewest","OriginalItemSpec":"wwwroot\\assets\\buttomB.png","FileLength":40501,"LastWriteTime":"2025-12-08T13:40:10.5343108+00:00"},"fbpW9ab7L1TaTnBuwiQwMgqEzT06/9VPn3k/59XfidI=":{"Identity":"C:\\Users\\53450061801\\Desktop\\TantoFaz\\Projeto-Grupo-Senai\\Back-End\\wwwroot\\assets\\charizard.png","SourceId":"BackEndProjeto","SourceType":"Discovered","ContentRoot":"C:\\Users\\53450061801\\Desktop\\TantoFaz\\Projeto-Grupo-Senai\\Back-End\\wwwroot\\","BasePath":"_content/BackEndProjeto","RelativePath":"assets/charizard#[.{fingerprint}]?.png","AssetKind":"All","AssetMode":"All","AssetRole":"Primary","AssetMergeBehavior":null,"AssetMergeSource":"","RelatedAsset":null,"AssetTraitName":null,"AssetTraitValue":null,"Fingerprint":"zh34dq22fz","Integrity":"SaDlfVhDRKOs0sO16x/\u002BjaQ5\u002BcT896mw9f4vefPK\u002B1c=","CopyToOutputDirectory":"Never","CopyToPublishDirectory":"PreserveNewest","OriginalItemSpec":"wwwroot\\assets\\charizard.png","FileLength":242360,"LastWriteTime":"2025-12-08T13:40:10.5343108+00:00"},"nItXDEA1DeleaiS9Lf9hU0aQRZvq\u002Bg2YciN97ML78kU=":{"Identity":"C:\\Users\\53450061801\\Desktop\\TantoFaz\\Projeto-Grupo-Senai\\Back-End\\wwwroot\\assets\\google.png","SourceId":"BackEndProjeto","SourceType":"Discovered","ContentRoot":"C:\\Users\\53450061801\\Desktop\\TantoFaz\\Projeto-Grupo-Senai\\Back-End\\wwwroot\\","BasePath":"_content/BackEndProjeto","RelativePath":"assets/google#[.{fingerprint}]?.png","AssetKind":"All","AssetMode":"All","AssetRole":"Primary","AssetMergeBehavior":null,"AssetMergeSource":"","RelatedAsset":null,"AssetTraitName":null,"AssetTraitValue":null,"Fingerprint":"8m0meg6cas","Integrity":"YOX/dgl20rr\u002B6aka8CYalogdRs5cfHVcHsRGByLUImc=","CopyToOutputDirectory":"Never","CopyToPublishDirectory":"PreserveNewest","OriginalItemSpec":"wwwroot\\assets\\google.png","FileLength":2359,"LastWriteTime":"2025-12-08T13:40:10.5343108+00:00"},"A8qVIH4AQ8ZeGJP8hU\u002BDgTDHZarVh0EeyS81XZa1QiY=":{"Identity":"C:\\Users\\53450061801\\Desktop\\TantoFaz\\Projeto-Grupo-Senai\\Back-End\\wwwroot\\assets\\joystick.png","SourceId":"BackEndProjeto","SourceType":"Discovered","ContentRoot":"C:\\Users\\53450061801\\Desktop\\TantoFaz\\Projeto-Grupo-Senai\\Back-End\\wwwroot\\","BasePath":"_content/BackEndProjeto","RelativePath":"assets/joystick#[.{fingerprint}]?.png","AssetKind":"All","AssetMode":"All","AssetRole":"Primary","AssetMergeBehavior":null,"AssetMergeSource":"","RelatedAsset":null,"AssetTraitName":null,"AssetTraitValue":null,"Fingerprint":"307rpnbdwl","Integrity":"M8GrkktDe4By3uZ\u002B5EyoAPwm32JE4YDDa0htRyQ0FGw=","CopyToOutputDirectory":"Never","CopyToPublishDirectory":"PreserveNewest","OriginalItemSpec":"wwwroot\\assets\\joystick.png","FileLength":6574,"LastWriteTime":"2025-12-08T13:40:10.5343108+00:00"},"OS5oPSXSHvBGniXKwUR4s/TOv\u002BMl/uBJZoB9H\u002BAju3k=":{"Identity":"C:\\Users\\53450061801\\Desktop\\TantoFaz\\Projeto-Grupo-Senai\\Back-End\\wwwroot\\assets\\lupa.svg","SourceId":"BackEndProjeto","SourceType":"Discovered","ContentRoot":"C:\\Users\\53450061801\\Desktop\\TantoFaz\\Projeto-Grupo-Senai\\Back-End\\wwwroot\\","BasePath":"_content/BackEndProjeto","RelativePath":"assets/lupa#[.{fingerprint}]?.svg","AssetKind":"All","AssetMode":"All","AssetRole":"Primary","AssetMergeBehavior":null,"AssetMergeSource":"","RelatedAsset":null,"AssetTraitName":null,"AssetTraitValue":null,"Fingerprint":"579xl9y3zr","Integrity":"L3qUXdEIbKWzM21b1j4x3FilZtoBC/d4rP7ILui\u002BouU=","CopyToOutputDirectory":"Never","CopyToPublishDirectory":"PreserveNewest","OriginalItemSpec":"wwwroot\\assets\\lupa.svg","FileLength":1903,"LastWriteTime":"2025-12-08T13:40:10.5343108+00:00"},"pf1/LId9cMv4\u002BKfSpl9vDNp/3iCmekL4pPybwRqzkHQ=":{"Identity":"C:\\Users\\53450061801\\Desktop\\TantoFaz\\Projeto-Grupo-Senai\\Back-End\\wwwroot\\assets\\pngwing.com.png","SourceId":"BackEndProjeto","SourceType":"Discovered","ContentRoot":"C:\\Users\\53450061801\\Desktop\\TantoFaz\\Projeto-Grupo-Senai\\Back-End\\wwwroot\\","BasePath":"_content/BackEndProjeto","RelativePath":"assets/pngwing.com#[.{fingerprint}]?.png","AssetKind":"All","AssetMode":"All","AssetRole":"Primary","AssetMergeBehavior":null,"AssetMergeSource":"","RelatedAsset":null,"AssetTraitName":null,"AssetTraitValue":null,"Fingerprint":"7uwfbq3btd","Integrity":"ASkrY6SY63CAYpdfrSGqVTEqj7MH23k3KU8BkntDAIM=","CopyToOutputDirectory":"Never","CopyToPublishDirectory":"PreserveNewest","OriginalItemSpec":"wwwroot\\assets\\pngwing.com.png","FileLength":61143,"LastWriteTime":"2025-12-08T13:40:10.5343108+00:00"},"R3QorycGvgV8LgfQhbXzgHkXPpI/LdEGN/s\u002Be3oaOB4=":{"Identity":"C:\\Users\\53450061801\\Desktop\\TantoFaz\\Projeto-Grupo-Senai\\Back-End\\wwwroot\\assets\\rlupa.svg","SourceId":"BackEndProjeto","SourceType":"Discovered","ContentRoot":"C:\\Users\\53450061801\\Desktop\\TantoFaz\\Projeto-Grupo-Senai\\Back-End\\wwwroot\\","BasePath":"_content/BackEndProjeto","RelativePath":"assets/rlupa#[.{fingerprint}]?.svg","AssetKind":"All","AssetMode":"All","AssetRole":"Primary","AssetMergeBehavior":null,"AssetMergeSource":"","RelatedAsset":null,"AssetTraitName":null,"AssetTraitValue":null,"Fingerprint":"n27yv52utg","Integrity":"T6vut/7mCeh84RKxthxzYdtLLTVvIlyXy9VndsUND1g=","CopyToOutputDirectory":"Never","CopyToPublishDirectory":"PreserveNewest","OriginalItemSpec":"wwwroot\\assets\\rlupa.svg","FileLength":1917,"LastWriteTime":"2025-12-08T13:40:10.5343108+00:00"},"hHYEBssbyj\u002BAB4XInZ/C\u002B0lAa7PTGfDAcJF75pH89tg=":{"Identity":"C:\\Users\\53450061801\\Desktop\\TantoFaz\\Projeto-Grupo-Senai\\Back-End\\wwwroot\\assets\\rseta.svg","SourceId":"BackEndProjeto","SourceType":"Discovered","ContentRoot":"C:\\Users\\53450061801\\Desktop\\TantoFaz\\Projeto-Grupo-Senai\\Back-End\\wwwroot\\","BasePath":"_content/BackEndProjeto","RelativePath":"assets/rseta#[.{fingerprint}]?.svg","AssetKind":"All","AssetMode":"All","AssetRole":"Primary","AssetMergeBehavior":null,"AssetMergeSource":"","RelatedAsset":null,"AssetTraitName":null,"AssetTraitValue":null,"Fingerprint":"aegj6krkaa","Integrity":"PuAdE7DQCNCt0gbwcQyzZmSxd0gDrgv\u002BRDU7aqRBGAw=","CopyToOutputDirectory":"Never","CopyToPublishDirectory":"PreserveNewest","OriginalItemSpec":"wwwroot\\assets\\rseta.svg","FileLength":664,"LastWriteTime":"2025-12-08T13:40:10.5343108+00:00"},"86UXLN0VsXeD05sU3sZBg33LTlPOtcxT2ewkBd7xloU=":{"Identity":"C:\\Users\\53450061801\\Desktop\\TantoFaz\\Projeto-Grupo-Senai\\Back-End\\wwwroot\\assets\\seta.svg","SourceId":"BackEndProjeto","SourceType":"Discovered","ContentRoot":"C:\\Users\\53450061801\\Desktop\\TantoFaz\\Projeto-Grupo-Senai\\Back-End\\wwwroot\\","BasePath":"_content/BackEndProjeto","RelativePath":"assets/seta#[.{fingerprint}]?.svg","AssetKind":"All","AssetMode":"All","AssetRole":"Primary","AssetMergeBehavior":null,"AssetMergeSource":"","RelatedAsset":null,"AssetTraitName":null,"AssetTraitValue":null,"Fingerprint":"ackcsvpagb","Integrity":"BobsM1hRJ12jAJJwal3BFndaNgyChR2HxSA\u002BwlF9wgA=","CopyToOutputDirectory":"Never","CopyToPublishDirectory":"PreserveNewest","OriginalItemSpec":"wwwroot\\assets\\seta.svg","FileLength":611,"LastWriteTime":"2025-12-08T13:40:10.5343108+00:00"},"FoEgunFimqb2nmqWmtBZ3MgsB3YFgLmCNyexXEQl20Q=":{"Identity":"C:\\Users\\53450061801\\Desktop\\TantoFaz\\Projeto-Grupo-Senai\\Back-End\\wwwroot\\assets\\setinhas.png","SourceId":"BackEndProjeto","SourceType":"Discovered","ContentRoot":"C:\\Users\\53450061801\\Desktop\\TantoFaz\\Projeto-Grupo-Senai\\Back-End\\wwwroot\\","BasePath":"_content/BackEndProjeto","RelativePath":"assets/setinhas#[.{fingerprint}]?.png","AssetKind":"All","AssetMode":"All","AssetRole":"Primary","AssetMergeBehavior":null,"AssetMergeSource":"","RelatedAsset":null,"AssetTraitName":null,"AssetTraitValue":null,"Fingerprint":"v39uerr2to","Integrity":"m9NL8M7jXioRz4EaUwmJz1euZJGEpO\u002B395MkCnK1EUs=","CopyToOutputDirectory":"Never","CopyToPublishDirectory":"PreserveNewest","OriginalItemSpec":"wwwroot\\assets\\setinhas.png","FileLength":21684,"LastWriteTime":"2025-12-08T13:40:10.5343108+00:00"},"KMF0x6KVdm5kW4UEzhnsnRLVdT0gIEaWkbwwVUBY/XQ=":{"Identity":"C:\\Users\\53450061801\\Desktop\\TantoFaz\\Projeto-Grupo-Senai\\Back-End\\wwwroot\\css\\cadastro.css","SourceId":"BackEndProjeto","SourceType":"Discovered","ContentRoot":"C:\\Users\\53450061801\\Desktop\\TantoFaz\\Projeto-Grupo-Senai\\Back-End\\wwwroot\\","BasePath":"_content/BackEndProjeto","RelativePath":"css/cadastro#[.{fingerprint}]?.css","AssetKind":"All","AssetMode":"All","AssetRole":"Primary","AssetMergeBehavior":null,"AssetMergeSource":"","RelatedAsset":null,"AssetTraitName":null,"AssetTraitValue":null,"Fingerprint":"q8kozvni40","Integrity":"ektbyk0dKfs7co7NP9Z/9Pa/tW9ZnVZ4O3rnU8IiBws=","CopyToOutputDirectory":"Never","CopyToPublishDirectory":"PreserveNewest","OriginalItemSpec":"wwwroot\\css\\cadastro.css","FileLength":8523,"LastWriteTime":"2025-12-08T13:40:10.5343108+00:00"},"o6Pw\u002BWEWGKy9wkWUfOE\u002BHYnAssDi62RF2Ai8tCuJ9Ic=":{"Identity":"C:\\Users\\53450061801\\Desktop\\TantoFaz\\Projeto-Grupo-Senai\\Back-End\\wwwroot\\css\\home.css","SourceId":"BackEndProjeto","SourceType":"Discovered","ContentRoot":"C:\\Users\\53450061801\\Desktop\\TantoFaz\\Projeto-Grupo-Senai\\Back-End\\wwwroot\\","BasePath":"_content/BackEndProjeto","RelativePath":"css/home#[.{fingerprint}]?.css","AssetKind":"All","AssetMode":"All","AssetRole":"Primary","AssetMergeBehavior":null,"AssetMergeSource":"","RelatedAsset":null,"AssetTraitName":null,"AssetTraitValue":null,"Fingerprint":"mi3i55y080","Integrity":"Tlua4UnOi\u002BBoKmQGM9y22k5fUcyFOqjUKJLqBOUs9vE=","CopyToOutputDirectory":"Never","CopyToPublishDirectory":"PreserveNewest","OriginalItemSpec":"wwwroot\\css\\home.css","FileLength":7420,"LastWriteTime":"2025-12-08T13:42:09.072794+00:00"},"PbZCF/3D0Mbo7UYP\u002B2Zf6lAFzOuBwpC9sUwzRR/cpW8=":{"Identity":"C:\\Users\\53450061801\\Desktop\\TantoFaz\\Projeto-Grupo-Senai\\Back-End\\wwwroot\\css\\login.css","SourceId":"BackEndProjeto","SourceType":"Discovered","ContentRoot":"C:\\Users\\53450061801\\Desktop\\TantoFaz\\Projeto-Grupo-Senai\\Back-End\\wwwroot\\","BasePath":"_content/BackEndProjeto","RelativePath":"css/login#[.{fingerprint}]?.css","AssetKind":"All","AssetMode":"All","AssetRole":"Primary","AssetMergeBehavior":null,"AssetMergeSource":"","RelatedAsset":null,"AssetTraitName":null,"AssetTraitValue":null,"Fingerprint":"6b1b235c58","Integrity":"nqYp\u002Bj1MDEieTjV0xaS8E9aT6QL5mkxz/uPXk6ihYJQ=","CopyToOutputDirectory":"Never","CopyToPublishDirectory":"PreserveNewest","OriginalItemSpec":"wwwroot\\css\\login.css","FileLength":10334,"LastWriteTime":"2025-12-08T13:40:10.5343108+00:00"},"HiTxlUnTXuQbm2l/MSBCJbfFBDv4d2XyWq4ZJPgC0F4=":{"Identity":"C:\\Users\\53450061801\\Desktop\\TantoFaz\\Projeto-Grupo-Senai\\Back-End\\wwwroot\\css\\senha.css","SourceId":"BackEndProjeto","SourceType":"Discovered","ContentRoot":"C:\\Users\\53450061801\\Desktop\\TantoFaz\\Projeto-Grupo-Senai\\Back-End\\wwwroot\\","BasePath":"_content/BackEndProjeto","RelativePath":"css/senha#[.{fingerprint}]?.css","AssetKind":"All","AssetMode":"All","AssetRole":"Primary","AssetMergeBehavior":null,"AssetMergeSource":"","RelatedAsset":null,"AssetTraitName":null,"AssetTraitValue":null,"Fingerprint":"2gha6h3521","Integrity":"0pDwZw7hLxgGIjr5MiyVVocSRNjy5MCs1VBzRK3lCYs=","CopyToOutputDirectory":"Never","CopyToPublishDirectory":"PreserveNewest","OriginalItemSpec":"wwwroot\\css\\senha.css","FileLength":1764,"LastWriteTime":"2025-12-08T13:40:10.5343108+00:00"},"zajGcXyfa5\u002BtC9UY35hn\u002BDnwdnCJJJ81SS95cRItiro=":{"Identity":"C:\\Users\\53450061801\\Desktop\\TantoFaz\\Projeto-Grupo-Senai\\Back-End\\wwwroot\\favicon.ico","SourceId":"BackEndProjeto","SourceType":"Discovered","ContentRoot":"C:\\Users\\53450061801\\Desktop\\TantoFaz\\Projeto-Grupo-Senai\\Back-End\\wwwroot\\","BasePath":"_content/BackEndProjeto","RelativePath":"favicon#[.{fingerprint}]?.ico","AssetKind":"All","AssetMode":"All","AssetRole":"Primary","AssetMergeBehavior":null,"AssetMergeSource":"","RelatedAsset":null,"AssetTraitName":null,"AssetTraitValue":null,"Fingerprint":"61n19gt1b8","Integrity":"Jtxf9L\u002B5ITKRc1gIRl4VbUpGkRNfOBXjYTdhJD4facM=","CopyToOutputDirectory":"Never","CopyToPublishDirectory":"PreserveNewest","OriginalItemSpec":"wwwroot\\favicon.ico","FileLength":5430,"LastWriteTime":"2025-12-08T13:40:10.5343108+00:00"},"PFV4kHpoKnYvrYVcP9Hjzl9R1SN598aybalaWiwBGos=":{"Identity":"C:\\Users\\53450061801\\Desktop\\TantoFaz\\Projeto-Grupo-Senai\\Back-End\\wwwroot\\js\\site.js","SourceId":"BackEndProjeto","SourceType":"Discovered","ContentRoot":"C:\\Users\\53450061801\\Desktop\\TantoFaz\\Projeto-Grupo-Senai\\Back-End\\wwwroot\\","BasePath":"_content/BackEndProjeto","RelativePath":"js/site#[.{fingerprint}]?.js","AssetKind":"All","AssetMode":"All","AssetRole":"Primary","AssetMergeBehavior":null,"AssetMergeSource":"","RelatedAsset":null,"AssetTraitName":null,"AssetTraitValue":null,"Fingerprint":"69dzlbtke7","Integrity":"JsGrgt2EU7fjO\u002BCC5SOS\u002B0VcB1\u002BzQ9oqzc7fNBx9HHc=","CopyToOutputDirectory":"Never","CopyToPublishDirectory":"PreserveNewest","OriginalItemSpec":"wwwroot\\js\\site.js","FileLength":4510,"LastWriteTime":"2025-12-08T13:41:53.7669729+00:00"}},"CachedCopyCandidates":{}}